{
  "1374854299762299001": {
    "messageId": "1374854299762299001",
    "channelId": "1374792366807846992",
    "formData": {
      "title": "1",
      "description": "1",
      "contact": "1"
    },
    "requiredVotes": 1,
    "currentVotes": 0,
    "voters": [],
    "forumChannelId": "1374848112568434731",
    "authorId": "757946225323671664"
  },
  "1374855588076458035": {
    "messageId": "1374855588076458035",
    "channelId": "1374792366807846992",
    "formData": {
      "title": "1",
      "description": "2",
      "contact": "2"
    },
    "requiredVotes": 1,
    "currentVotes": 1,
    "voters": [
      "757946225323671664"
    ],
    "forumChannelId": "1374848112568434731",
    "authorId": "757946225323671664",
    "status": "posted",
    "threadId": "1374855625619542028"
  },
  "1374860882974081036": {
    "messageId": "1374860882974081036",
    "channelId": "1235691065386995796",
    "formData": {
      "title": "1",
      "reason": "2",
      "motion": "2",
      "implementation": "343",
      "voteTime": "2323"
    },
    "requiredVotes": 1,
    "currentVotes": 1,
    "voters": [
      "757946225323671664"
    ],
    "forumChannelId": "1374848112568434731",
    "authorId": "757946225323671664"
  },
  "1374861417940779050": {
    "messageId": "1374861417940779050",
    "channelId": "1374792366807846992",
    "formData": {
      "title": "1",
      "reason": "2",
      "motion": "23",
      "implementation": "23",
      "voteTime": "23"
    },
    "requiredVotes": 1,
    "currentVotes": 1,
    "voters": [
      "757946225323671664"
    ],
    "forumChannelId": "1374848112568434731",
    "authorId": "757946225323671664"
  },
  "1374862669487800461": {
    "messageId": "1374862669487800461",
    "channelId": "1374792366807846992",
    "formData": {
      "title": "12",
      "reason": "2323",
      "motion": "2323",
      "implementation": "2131",
      "voteTime": "123123"
    },
    "requiredVotes": 1,
    "currentVotes": 1,
    "voters": [
      "757946225323671664"
    ],
    "forumChannelId": "1374848112568434731",
    "authorId": "757946225323671664",
    "status": "posted",
    "threadId": "1374862698407268442"
  },
  "1374863655421739080": {
    "messageId": "1374863655421739080",
    "channelId": "1374792366807846992",
    "formData": {
      "title": "标题",
      "reason": "原因",
      "motion": "动议",
      "implementation": "方案",
      "voteTime": "时间"
    },
    "requiredVotes": 4,
    "currentVotes": 0,
    "voters": [],
    "forumChannelId": "1374848112568434731",
    "authorId": "757946225323671664"
  },
  "1374868415805788163": {
    "messageId": "1374868415805788163",
    "channelId": "1374792366807846992",
    "shortId": "573494",
    "formData": {
      "title": "标题",
      "reason": "232",
      "motion": "2323",
      "implementation": "2313",
      "voteTime": "123131"
    },
    "requiredVotes": 4,
    "currentVotes": 1,
    "voters": [
      "757946225323671664"
    ],
    "forumChannelId": "1374848112568434731",
    "authorId": "757946225323671664",
    "deadline": "2025-05-22T21:56:13.493Z",
    "status": "pending"
  },
  "1374870294287880357": {
    "messageId": "1374870294287880357",
    "channelId": "1374792366807846992",
    "shortId": "021195",
    "formData": {
      "title": "12",
      "reason": "23",
      "motion": "23",
      "implementation": "323",
      "voteTime": "2323"
    },
    "requiredVotes": 4,
    "currentVotes": 0,
    "voters": [],
    "forumChannelId": "1374848112568434731",
    "authorId": "757946225323671664",
    "deadline": "2025-05-22T22:03:41.195Z",
    "status": "pending"
  },
  "1374871693180403873": {
    "messageId": "1374871693180403873",
    "channelId": "1374792366807846992",
    "proposalId": 1,
    "formData": {
      "title": "标题",
      "reason": "12",
      "motion": "12",
      "implementation": "232",
      "voteTime": "23232"
    },
    "requiredVotes": 4,
    "currentVotes": 0,
    "voters": [],
    "forumChannelId": "1374848112568434731",
    "authorId": "757946225323671664",
    "deadline": "2025-05-22T22:09:14.646Z",
    "status": "pending"
  }
}